bitresource/__init__.py
bitresource/exchange.py
bitresource/utils.py
bitresource/binance/__init__.py
bitresource/binance/resources.py
bitresource/bitpay/__init__.py
bitresource/bitpay/resources.py
bitresource/bitstamp/__init__.py
bitresource/bittrex/__init__.py
bitresource/bittrex/resources.py
bitresource/blockchain/__init__.py
bitresource/blockchain/resources.py
bitresource/blockchain/utils.py
bitresource/coinbase/__init__.py
bitresource/coinbase/auth.py
bitresource/coinbase/models.py
bitresource/coindesk/__init__.py
bitresource/coindesk/resources.py
bitresource/coindesk/utils.py
bitresource/kraken/__init__.py
bitresource/kraken/resources.py
bitresource/kraken/utils.py
bitresource-0.1.1.dist-info/DESCRIPTION.rst
bitresource-0.1.1.dist-info/METADATA
bitresource-0.1.1.dist-info/RECORD
bitresource-0.1.1.dist-info/WHEEL
bitresource-0.1.1.dist-info/metadata.json
bitresource-0.1.1.dist-info/top_level.txt
