Metadata-Version: 2.0
Name: bitresource
Version: 0.1.1
Summary: Crypto Currency Resource Library
Home-page: https://github.com/hbasria/bitresource
Author: Hasan Basri
Author-email: hbasria@gmail.com
License: MIT
Keywords: Crypto Currency Library
Platform: UNKNOWN
Classifier: Development Status :: 4 - Beta
Classifier: Intended Audience :: Developers
Classifier: License :: OSI Approved :: MIT License
Classifier: Programming Language :: Python
Classifier: Programming Language :: Python :: 2
Classifier: Programming Language :: Python :: 2.7
Classifier: Programming Language :: Python :: 3
Classifier: Programming Language :: Python :: 3.3
Classifier: Programming Language :: Python :: 3.4
Classifier: Topic :: Software Development
Classifier: Topic :: Software Development :: Libraries :: Python Modules
